compatlib/__init__.py
compatlib/utils.py
compatlib/client/__init__.py
compatlib/client/analyze_recording.py
compatlib/client/models.py
compatlib/client/perfetto.py
compatlib/client/plot_recording.py
compatlib/graph/__init__.py
compatlib/graph/filesystem.py
compatlib/logger/__init__.py
compatlib/logger/generate.py
compatlib/logger/logger.py
compatlib/models/__init__.py
compatlib/models/distance.py
compatlib/models/markov.py
compatlib/traces/__init__.py
compatlib/traces/traces.py
compatlib-0.0.11.dist-info/LICENSE
compatlib-0.0.11.dist-info/METADATA
compatlib-0.0.11.dist-info/NOTICE
compatlib-0.0.11.dist-info/WHEEL
compatlib-0.0.11.dist-info/entry_points.txt
compatlib-0.0.11.dist-info/top_level.txt
compatlib-0.0.11.dist-info/RECORD
