Metadata-Version: 2.1
Name: compatlib
Version: 0.0.11
Summary: Helper tool to install and configure Flux Framework
Home-page: https://github.com/compspec/compat-lib
Author: Vanessasaurus
Author-email: vsoch@users.noreply.github.com
Maintainer: Vanessasaurus
License: MIT
Keywords: fuse,filesystem,recorder,compatibility
Classifier: Intended Audience :: Science/Research
Classifier: Intended Audience :: Developers
Classifier: License :: OSI Approved :: Apache Software License
Classifier: Programming Language :: Python
Classifier: Topic :: Software Development
Classifier: Topic :: Scientific/Engineering
Classifier: Operating System :: Unix
Classifier: Programming Language :: Python :: 3.11
License-File: LICENSE
License-File: NOTICE
Requires-Dist: pyyaml
Requires-Dist: networkx
Requires-Dist: numpy
Requires-Dist: seaborn
Requires-Dist: pandas
Requires-Dist: matplotlib
Requires-Dist: scipy
